radarwave/__init__.py
radarwave/seadarq.py
radarwave-0.0.2.dist-info/LICENSE
radarwave-0.0.2.dist-info/METADATA
radarwave-0.0.2.dist-info/WHEEL
radarwave-0.0.2.dist-info/top_level.txt
radarwave-0.0.2.dist-info/RECORD
