Metadata-Version: 2.1
Name: radarwave
Version: 0.0.2
Summary: Support using X-band radar measurements to analyse sea surface waves
Home-page: https://github.com/mikeridgill/radarwave
Author: Michael Ridgill
Author-email: mike@mikeridgill.com
Classifier: Programming Language :: Python :: 3
Classifier: License :: OSI Approved :: GNU General Public License v3 (GPLv3)
Classifier: Operating System :: OS Independent
License-File: LICENSE
